plonetheme/__init__.py
plonetheme/deliberations/__init__.py
plonetheme/deliberations/configure.zcml
plonetheme/deliberations/interfaces.py
plonetheme/deliberations/package-lock.json
plonetheme/deliberations/permissions.zcml
plonetheme/deliberations/setuphandlers.py
plonetheme/deliberations/browser/__init__.py
plonetheme/deliberations/browser/configure.zcml
plonetheme/deliberations/browser/overrides/.gitkeep
plonetheme/deliberations/browser/overrides/collective.querynextprev.browser.templates.nextprev.pt
plonetheme/deliberations/browser/overrides/eea.facetednavigation.browser.template.view.pt
plonetheme/deliberations/browser/static/.gitkeep
plonetheme/deliberations/locales/README.rst
plonetheme/deliberations/locales/__init__.py
plonetheme/deliberations/locales/plonetheme.deliberations.pot
plonetheme/deliberations/locales/update.py
plonetheme/deliberations/locales/update.sh
plonetheme/deliberations/locales/en/LC_MESSAGES/plonetheme.deliberations.po
plonetheme/deliberations/profiles/default/browserlayer.xml
plonetheme/deliberations/profiles/default/catalog.xml
plonetheme/deliberations/profiles/default/metadata.xml
plonetheme/deliberations/profiles/default/rolemap.xml
plonetheme/deliberations/profiles/default/theme.xml
plonetheme/deliberations/profiles/default/registry/main.xml
plonetheme/deliberations/profiles/uninstall/browserlayer.xml
plonetheme/deliberations/profiles/uninstall/theme.xml
plonetheme/deliberations/theme/README.rst
plonetheme/deliberations/theme/barceloneta-apple-touch-icon-114x114-precomposed.png
plonetheme/deliberations/theme/barceloneta-apple-touch-icon-144x144-precomposed.png
plonetheme/deliberations/theme/barceloneta-apple-touch-icon-57x57-precomposed.png
plonetheme/deliberations/theme/barceloneta-apple-touch-icon-72x72-precomposed.png
plonetheme/deliberations/theme/barceloneta-apple-touch-icon-precomposed.png
plonetheme/deliberations/theme/barceloneta-apple-touch-icon.png
plonetheme/deliberations/theme/barceloneta-favicon.ico
plonetheme_deliberations-1.4.dist-info/licenses/LICENSE.GPL
plonetheme_deliberations-1.4.dist-info/licenses/LICENSE.rst
plonetheme_deliberations-1.4.dist-info/METADATA
plonetheme_deliberations-1.4.dist-info/WHEEL
plonetheme_deliberations-1.4.dist-info/entry_points.txt
plonetheme_deliberations-1.4.dist-info/top_level.txt
plonetheme_deliberations-1.4.dist-info/RECORD
